.DS_Store
TaiwanNewsCrawler/LICENSE.py
TaiwanNewsCrawler/NewsCrawler.py
TaiwanNewsCrawler/TaiwanNewsCrawler.py
TaiwanNewsCrawler/__init__.py
Taiwan_News_Crawler/LICENSE.py
Taiwan_News_Crawler/TaiwanNewsCrawler.py
Taiwan_News_Crawler/Taiwan_News_Crawler.py
Taiwan_News_Crawler/__init__.py
Taiwan_News_Crawler-2020.2.15.dist-info/LICENSE.txt
Taiwan_News_Crawler-2020.2.15.dist-info/METADATA
Taiwan_News_Crawler-2020.2.15.dist-info/WHEEL
Taiwan_News_Crawler-2020.2.15.dist-info/top_level.txt
Taiwan_News_Crawler-2020.2.15.dist-info/RECORD
