Metadata-Version: 2.1
Name: Taiwan-News-Crawler
Version: 2020.2.15
Summary: A political news crawler for 34 Taiwanese stream media.
Home-page: https://github.com/milkpool/Taiwan_News_Crawler
Author: RitaLiou
Author-email: imritaliou@gmail.com
License: MIT
Keywords: news crawler Taiwan politics
Platform: UNKNOWN
Classifier: Programming Language :: Python :: 2
Classifier: Programming Language :: Python :: 3
Classifier: License :: OSI Approved :: MIT License
Classifier: Operating System :: OS Independent
Requires-Dist: requests
Requires-Dist: bs4
Requires-Dist: selenium
